<annotation>
	<folder>JPEGImages</folder>
	<filename>IMG_1905.jpg</filename>
	<path>G:\IFUDA2022\voc3\JPEGImages\IMG_1905.jpg</path>
	<source>
		<database>Unknown</database>
	</source>
	<size>
		<width>640</width>
		<height>480</height>
		<depth>3</depth>
	</size>
	<segmented>0</segmented>
	<object>
		<name>czjyz_sl</name>
		<pose>Unspecified</pose>
		<truncated>0</truncated>
		<difficult>0</difficult>
		<bndbox>
			<xmin>260</xmin>
			<ymin>221</ymin>
			<xmax>372</xmax>
			<ymax>328</ymax>
		</bndbox>
	</object>
</annotation>
