<annotation>
	<folder>JPEGImages</folder>
	<filename>12345672.jpg</filename>
	<path>C:\Users\huang\Desktop\voc1\JPEGImages\12345672.jpg</path>
	<source>
		<database>Unknown</database>
	</source>
	<size>
		<width>4608</width>
		<height>3456</height>
		<depth>3</depth>
	</size>
	<segmented>0</segmented>
	<object>
		<name>blq_yxdk</name>
		<pose>Unspecified</pose>
		<truncated>0</truncated>
		<difficult>0</difficult>
		<bndbox>
			<xmin>1691</xmin>
			<ymin>1298</ymin>
			<xmax>2380</xmax>
			<ymax>1777</ymax>
		</bndbox>
	</object>
</annotation>
