<annotation>
	<folder>JPEGImages</folder>
	<filename>jyz-ps2151.jpg</filename>
	<path>G:\IFUDA2023\voc8\JPEGImages\jyz-ps2151.jpg</path>
	<source>
		<database>Unknown</database>
	</source>
	<size>
		<width>4608</width>
		<height>3456</height>
		<depth>3</depth>
	</size>
	<segmented>0</segmented>
	<object>
		<name>czjyz_ps</name>
		<pose>Unspecified</pose>
		<truncated>0</truncated>
		<difficult>0</difficult>
		<bndbox>
			<xmin>1784</xmin>
			<ymin>1484</ymin>
			<xmax>2524</xmax>
			<ymax>1752</ymax>
		</bndbox>
	</object>
	<object>
		<name>czjyz_ps</name>
		<pose>Unspecified</pose>
		<truncated>0</truncated>
		<difficult>0</difficult>
		<bndbox>
			<xmin>1523</xmin>
			<ymin>1813</ymin>
			<xmax>1809</xmax>
			<ymax>2124</ymax>
		</bndbox>
	</object>
</annotation>
