<annotation>
	<folder>JPEGImages</folder>
	<filename>jyz-ps1854.jpg</filename>
	<path>G:\IFUDA2023\voc8\JPEGImages\jyz-ps1854.jpg</path>
	<source>
		<database>Unknown</database>
	</source>
	<size>
		<width>5184</width>
		<height>3888</height>
		<depth>3</depth>
	</size>
	<segmented>0</segmented>
	<object>
		<name>czjyz_ps</name>
		<pose>Unspecified</pose>
		<truncated>0</truncated>
		<difficult>0</difficult>
		<bndbox>
			<xmin>2314</xmin>
			<ymin>3122</ymin>
			<xmax>3434</xmax>
			<ymax>3931</ymax>
		</bndbox>
	</object>
	<object>
		<name>czjyz_ps</name>
		<pose>Unspecified</pose>
		<truncated>0</truncated>
		<difficult>0</difficult>
		<bndbox>
			<xmin>2536</xmin>
			<ymin>2044</ymin>
			<xmax>2973</xmax>
			<ymax>2302</ymax>
		</bndbox>
	</object>
	<object>
		<name>czjyz_ps</name>
		<pose>Unspecified</pose>
		<truncated>0</truncated>
		<difficult>0</difficult>
		<bndbox>
			<xmin>3523</xmin>
			<ymin>2373</ymin>
			<xmax>3832</xmax>
			<ymax>2665</ymax>
		</bndbox>
	</object>
</annotation>
