<annotation>
	<folder>IFUDA2022</folder>
	<filename>jyz-ps2841.jpg</filename>
	<path>IFUDA2022/jyz-ps2841.jpg</path>
	<source>
		<database>IFUDA-配网缺陷检测</database>
	</source>
	<size>
		<width>4608</width>
		<height>3456</height>
		<depth>3</depth>
	</size>
	<segmented>0</segmented>
	<object>
		<name>czjyz_ps</name>
		<pose>Unspecified</pose>
		<truncated>0</truncated>
		<difficult>0</difficult>
		<bndbox>
			<xmin>62</xmin>
			<ymin>1158</ymin>
			<xmax>4559</xmax>
			<ymax>2553</ymax>
		</bndbox>
	</object>
</annotation>