<annotation>
	<folder>IFUDA2022</folder>
	<filename>IMG_0466.jpg</filename>
	<path>IFUDA2022/IMG_0466.jpg</path>
	<source>
		<database>IFUDA-配网缺陷检测</database>
	</source>
	<size>
		<width>640</width>
		<height>480</height>
		<depth>3</depth>
	</size>
	<segmented>0</segmented>
	<object>
		<name>dx_jypps</name>
		<pose>Unspecified</pose>
		<truncated>0</truncated>
		<difficult>0</difficult>
		<bndbox>
			<xmin>179</xmin>
			<ymin>287</ymin>
			<xmax>258</xmax>
			<ymax>379</ymax>
		</bndbox>
	</object>
</annotation>